ehr_utils_utils/__init__.py
ehr_utils_utils/fake_files.py
ehr_utils_utils-0.1.0.dist-info/METADATA
ehr_utils_utils-0.1.0.dist-info/WHEEL
ehr_utils_utils-0.1.0.dist-info/top_level.txt
ehr_utils_utils-0.1.0.dist-info/RECORD
