Metadata-Version: 2.4
Name: ehr_utils_utils
Version: 0.1.0
Summary: Utilities for building and maintaining EHR utilities.
Author-email: Patrick Wang <patrick.wang@duke.edu>
License-Expression: MIT
Project-URL: Homepage, https://github.com/biostat821/ehr-utils-utils
Project-URL: Issues, https://github.com/biostat821/ehr-utils-utils/issues
Classifier: Programming Language :: Python :: 3
Classifier: Operating System :: OS Independent
Requires-Python: >=3.9
